charchef/LICENSE
charchef/README.MD
charchef/__init__.py
charchef/requirements.txt
charchef/thirdparty.json
charchef-0.12.dist-info/LICENSE.rst
charchef-0.12.dist-info/METADATA
charchef-0.12.dist-info/WHEEL
charchef-0.12.dist-info/top_level.txt
charchef-0.12.dist-info/RECORD
